[{"Position":{"X":-48.0,"Y":-14.0,"Z":0.0},"Mass":9995.0,"Velocity":{"X":0.0,"Y":0.0,"Z":0.0},"Force":{"X":0.0,"Y":0.0,"Z":0.0},"Density":9999.0,"IsGone":false,"BounceCount":0,"Radius":0.620267758195335},{"Position":{"X":68.0,"Y":29.0,"Z":0.0},"Mass":16700.0,"Velocity":{"X":0.0,"Y":0.0,"Z":0.0},"Force":{"X":0.0,"Y":0.0,"Z":0.0},"Density":9999.0,"IsGone":false,"BounceCount":0,"Radius":0.7360213820643443},{"Position":{"X":44.0,"Y":-47.0,"Z":0.0},"Mass":19955.0,"Velocity":{"X":0.0,"Y":0.0,"Z":0.0},"Force":{"X":0.0,"Y":0.0,"Z":0.0},"Density":9999.0,"IsGone":false,"BounceCount":0,"Radius":0.781032042388455},{"Position":{"X":-12.0,"Y":15.0,"Z":0.0},"Mass":17652.0,"Velocity":{"X":0.0,"Y":0.0,"Z":0.0},"Force":{"X":0.0,"Y":0.0,"Z":0.0},"Density":9999.0,"IsGone":false,"BounceCount":0,"Radius":0.749749607423871},{"Position":{"X":26.0,"Y":36.0,"Z":0.0},"Mass":10408.0,"Velocity":{"X":0.0,"Y":0.0,"Z":0.0},"Force":{"X":0.0,"Y":0.0,"Z":0.0},"Density":9999.0,"IsGone":false,"BounceCount":0,"Radius":0.6286960068654287},{"Position":{"X":12.0,"Y":-7.0,"Z":0.0},"Mass":3654.0,"Velocity":{"X":0.0,"Y":0.0,"Z":0.0},"Force":{"X":0.0,"Y":0.0,"Z":0.0},"Density":9999.0,"IsGone":false,"BounceCount":0,"Radius":0.4435144647456999},{"Position":{"X":37.0,"Y":20.0,"Z":0.0},"Mass":18229.0,"Velocity":{"X":0.0,"Y":0.0,"Z":0.0},"Force":{"X":0.0,"Y":0.0,"Z":0.0},"Density":9999.0,"IsGone":false,"BounceCount":0,"Radius":0.7578313299811923},{"Position":{"X":-25.0,"Y":4.0,"Z":0.0},"Mass":4769.0,"Velocity":{"X":0.0,"Y":0.0,"Z":0.0},"Force":{"X":0.0,"Y":0.0,"Z":0.0},"Density":9999.0,"IsGone":false,"BounceCount":0,"Radius":0.4846862672562712},{"Position":{"X":70.0,"Y":20.0,"Z":0.0},"Mass":12966.0,"Velocity":{"X":0.0,"Y":0.0,"Z":0.0},"Force":{"X":0.0,"Y":0.0,"Z":0.0},"Density":9999.0,"IsGone":false,"BounceCount":0,"Radius":0.6764779001369259},{"Position":{"X":6.0,"Y":43.0,"Z":0.0},"Mass":18543.0,"Velocity":{"X":0.0,"Y":0.0,"Z":0.0},"Force":{"X":0.0,"Y":0.0,"Z":0.0},"Density":9999.0,"IsGone":false,"BounceCount":0,"Radius":0.7621578730179533},{"Position":{"X":-44.0,"Y":-10.0,"Z":0.0},"Mass":4689.0,"Velocity":{"X":0.0,"Y":0.0,"Z":0.0},"Force":{"X":0.0,"Y":0.0,"Z":0.0},"Density":9999.0,"IsGone":false,"BounceCount":0,"Radius":0.4819607649665134},{"Position":{"X":-72.0,"Y":49.0,"Z":0.0},"Mass":5116.0,"Velocity":{"X":0.0,"Y":0.0,"Z":0.0},"Force":{"X":0.0,"Y":0.0,"Z":0.0},"Density":9999.0,"IsGone":false,"BounceCount":0,"Radius":0.4961676588364218},{"Position":{"X":-27.0,"Y":38.0,"Z":0.0},"Mass":9857.0,"Velocity":{"X":0.0,"Y":0.0,"Z":0.0},"Force":{"X":0.0,"Y":0.0,"Z":0.0},"Density":9999.0,"IsGone":false,"BounceCount":0,"Radius":0.6173998594655024},{"Position":{"X":-6.0,"Y":-19.0,"Z":0.0},"Mass":16659.0,"Velocity":{"X":0.0,"Y":0.0,"Z":0.0},"Force":{"X":0.0,"Y":0.0,"Z":0.0},"Density":9999.0,"IsGone":false,"BounceCount":0,"Radius":0.7354185555962647},{"Position":{"X":29.0,"Y":-15.0,"Z":0.0},"Mass":10277.0,"Velocity":{"X":0.0,"Y":0.0,"Z":0.0},"Force":{"X":0.0,"Y":0.0,"Z":0.0},"Density":9999.0,"IsGone":false,"BounceCount":0,"Radius":0.6260471742148397},{"Position":{"X":-34.0,"Y":-10.0,"Z":0.0},"Mass":7713.0,"Velocity":{"X":0.0,"Y":0.0,"Z":0.0},"Force":{"X":0.0,"Y":0.0,"Z":0.0},"Density":9999.0,"IsGone":false,"BounceCount":0,"Radius":0.5689307199755829},{"Position":{"X":77.0,"Y":-11.0,"Z":0.0},"Mass":10883.0,"Velocity":{"X":0.0,"Y":0.0,"Z":0.0},"Force":{"X":0.0,"Y":0.0,"Z":0.0},"Density":9999.0,"IsGone":false,"BounceCount":0,"Radius":0.6381182279574829},{"Position":{"X":16.0,"Y":37.0,"Z":0.0},"Mass":7135.0,"Velocity":{"X":0.0,"Y":0.0,"Z":0.0},"Force":{"X":0.0,"Y":0.0,"Z":0.0},"Density":9999.0,"IsGone":false,"BounceCount":0,"Radius":0.554348572167207},{"Position":{"X":-67.0,"Y":39.0,"Z":0.0},"Mass":11644.0,"Velocity":{"X":0.0,"Y":0.0,"Z":0.0},"Force":{"X":0.0,"Y":0.0,"Z":0.0},"Density":9999.0,"IsGone":false,"BounceCount":0,"Radius":0.652658010899449},{"Position":{"X":-18.0,"Y":28.0,"Z":0.0},"Mass":18410.0,"Velocity":{"X":0.0,"Y":0.0,"Z":0.0},"Force":{"X":0.0,"Y":0.0,"Z":0.0},"Density":9999.0,"IsGone":false,"BounceCount":0,"Radius":0.7603313019909061},{"Position":{"X":14.0,"Y":46.0,"Z":0.0},"Mass":10442.0,"Velocity":{"X":0.0,"Y":0.0,"Z":0.0},"Force":{"X":0.0,"Y":0.0,"Z":0.0},"Density":9999.0,"IsGone":false,"BounceCount":0,"Radius":0.6293798535953706},{"Position":{"X":38.0,"Y":-8.0,"Z":0.0},"Mass":18062.0,"Velocity":{"X":0.0,"Y":0.0,"Z":0.0},"Force":{"X":0.0,"Y":0.0,"Z":0.0},"Density":9999.0,"IsGone":false,"BounceCount":0,"Radius":0.7555100052388122},{"Position":{"X":75.0,"Y":21.0,"Z":0.0},"Mass":15763.0,"Velocity":{"X":0.0,"Y":0.0,"Z":0.0},"Force":{"X":0.0,"Y":0.0,"Z":0.0},"Density":9999.0,"IsGone":false,"BounceCount":0,"Radius":0.7219900835466987},{"Position":{"X":-42.0,"Y":12.0,"Z":0.0},"Mass":19098.0,"Velocity":{"X":0.0,"Y":0.0,"Z":0.0},"Force":{"X":0.0,"Y":0.0,"Z":0.0},"Density":9999.0,"IsGone":false,"BounceCount":0,"Radius":0.7696871519050474},{"Position":{"X":-41.0,"Y":34.0,"Z":0.0},"Mass":6219.0,"Velocity":{"X":0.0,"Y":0.0,"Z":0.0},"Force":{"X":0.0,"Y":0.0,"Z":0.0},"Density":9999.0,"IsGone":false,"BounceCount":0,"Radius":0.5295314916514636},{"Position":{"X":12.0,"Y":20.0,"Z":0.0},"Mass":7152.0,"Velocity":{"X":0.0,"Y":0.0,"Z":0.0},"Force":{"X":0.0,"Y":0.0,"Z":0.0},"Density":9999.0,"IsGone":false,"BounceCount":0,"Radius":0.5547884904606363},{"Position":{"X":-8.0,"Y":13.0,"Z":0.0},"Mass":2454.0,"Velocity":{"X":0.0,"Y":0.0,"Z":0.0},"Force":{"X":0.0,"Y":0.0,"Z":0.0},"Density":9999.0,"IsGone":false,"BounceCount":0,"Radius":0.38839753077928296},{"Position":{"X":16.0,"Y":42.0,"Z":0.0},"Mass":18434.0,"Velocity":{"X":0.0,"Y":0.0,"Z":0.0},"Force":{"X":0.0,"Y":0.0,"Z":0.0},"Density":9999.0,"IsGone":false,"BounceCount":0,"Radius":0.7606615577831107},{"Position":{"X":-23.0,"Y":-16.0,"Z":0.0},"Mass":19511.0,"Velocity":{"X":0.0,"Y":0.0,"Z":0.0},"Force":{"X":0.0,"Y":0.0,"Z":0.0},"Density":9999.0,"IsGone":false,"BounceCount":0,"Radius":0.7751958702646834},{"Position":{"X":-64.0,"Y":-47.0,"Z":0.0},"Mass":15085.0,"Velocity":{"X":0.0,"Y":0.0,"Z":0.0},"Force":{"X":0.0,"Y":0.0,"Z":0.0},"Density":9999.0,"IsGone":false,"BounceCount":0,"Radius":0.7114865790244852},{"Position":{"X":33.0,"Y":6.0,"Z":0.0},"Mass":6181.0,"Velocity":{"X":0.0,"Y":0.0,"Z":0.0},"Force":{"X":0.0,"Y":0.0,"Z":0.0},"Density":9999.0,"IsGone":false,"BounceCount":0,"Radius":0.5284507540920974},{"Position":{"X":-35.0,"Y":-43.0,"Z":0.0},"Mass":11046.0,"Velocity":{"X":0.0,"Y":0.0,"Z":0.0},"Force":{"X":0.0,"Y":0.0,"Z":0.0},"Density":9999.0,"IsGone":false,"BounceCount":0,"Radius":0.6412882565505392},{"Position":{"X":59.0,"Y":-6.0,"Z":0.0},"Mass":7162.0,"Velocity":{"X":0.0,"Y":0.0,"Z":0.0},"Force":{"X":0.0,"Y":0.0,"Z":0.0},"Density":9999.0,"IsGone":false,"BounceCount":0,"Radius":0.5550469403677957},{"Position":{"X":-32.0,"Y":-20.0,"Z":0.0},"Mass":18640.0,"Velocity":{"X":0.0,"Y":0.0,"Z":0.0},"Force":{"X":0.0,"Y":0.0,"Z":0.0},"Density":9999.0,"IsGone":false,"BounceCount":0,"Radius":0.7634845331565878},{"Position":{"X":-23.0,"Y":-33.0,"Z":0.0},"Mass":3301.0,"Velocity":{"X":0.0,"Y":0.0,"Z":0.0},"Force":{"X":0.0,"Y":0.0,"Z":0.0},"Density":9999.0,"IsGone":false,"BounceCount":0,"Radius":0.42874603380674864},{"Position":{"X":38.0,"Y":-45.0,"Z":0.0},"Mass":12967.0,"Velocity":{"X":0.0,"Y":0.0,"Z":0.0},"Force":{"X":0.0,"Y":0.0,"Z":0.0},"Density":9999.0,"IsGone":false,"BounceCount":0,"Radius":0.6764952907613746},{"Position":{"X":-5.0,"Y":-17.0,"Z":0.0},"Mass":15347.0,"Velocity":{"X":0.0,"Y":0.0,"Z":0.0},"Force":{"X":0.0,"Y":0.0,"Z":0.0},"Density":9999.0,"IsGone":false,"BounceCount":0,"Radius":0.7155820508161856},{"Position":{"X":-45.0,"Y":41.0,"Z":0.0},"Mass":3880.0,"Velocity":{"X":0.0,"Y":0.0,"Z":0.0},"Force":{"X":0.0,"Y":0.0,"Z":0.0},"Density":9999.0,"IsGone":false,"BounceCount":0,"Radius":0.45247596608068963},{"Position":{"X":-71.0,"Y":40.0,"Z":0.0},"Mass":2050.0,"Velocity":{"X":0.0,"Y":0.0,"Z":0.0},"Force":{"X":0.0,"Y":0.0,"Z":0.0},"Density":9999.0,"IsGone":false,"BounceCount":0,"Radius":0.3657937053594116},{"Position":{"X":-30.0,"Y":18.0,"Z":0.0},"Mass":13349.0,"Velocity":{"X":0.0,"Y":0.0,"Z":0.0},"Force":{"X":0.0,"Y":0.0,"Z":0.0},"Density":9999.0,"IsGone":false,"BounceCount":0,"Radius":0.6830741522381726},{"Position":{"X":26.0,"Y":41.0,"Z":0.0},"Mass":8065.0,"Velocity":{"X":0.0,"Y":0.0,"Z":0.0},"Force":{"X":0.0,"Y":0.0,"Z":0.0},"Density":9999.0,"IsGone":false,"BounceCount":0,"Radius":0.5774571077882914},{"Position":{"X":-58.0,"Y":2.0,"Z":0.0},"Mass":5126.0,"Velocity":{"X":0.0,"Y":0.0,"Z":0.0},"Force":{"X":0.0,"Y":0.0,"Z":0.0},"Density":9999.0,"IsGone":false,"BounceCount":0,"Radius":0.4964907268133911},{"Position":{"X":-74.0,"Y":40.0,"Z":0.0},"Mass":8375.0,"Velocity":{"X":0.0,"Y":0.0,"Z":0.0},"Force":{"X":0.0,"Y":0.0,"Z":0.0},"Density":9999.0,"IsGone":false,"BounceCount":0,"Radius":0.584762991724097},{"Position":{"X":-76.0,"Y":-48.0,"Z":0.0},"Mass":4178.0,"Velocity":{"X":0.0,"Y":0.0,"Z":0.0},"Force":{"X":0.0,"Y":0.0,"Z":0.0},"Density":9999.0,"IsGone":false,"BounceCount":0,"Radius":0.4637754469730462},{"Position":{"X":21.0,"Y":-23.0,"Z":0.0},"Mass":2651.0,"Velocity":{"X":0.0,"Y":0.0,"Z":0.0},"Force":{"X":0.0,"Y":0.0,"Z":0.0},"Density":9999.0,"IsGone":false,"BounceCount":0,"Radius":0.39852433890061373},{"Position":{"X":-70.0,"Y":-13.0,"Z":0.0},"Mass":7665.0,"Velocity":{"X":0.0,"Y":0.0,"Z":0.0},"Force":{"X":0.0,"Y":0.0,"Z":0.0},"Density":9999.0,"IsGone":false,"BounceCount":0,"Radius":0.5677480620867691},{"Position":{"X":-19.0,"Y":10.0,"Z":0.0},"Mass":10753.0,"Velocity":{"X":0.0,"Y":0.0,"Z":0.0},"Force":{"X":0.0,"Y":0.0,"Z":0.0},"Density":9999.0,"IsGone":false,"BounceCount":0,"Radius":0.6355672191550612},{"Position":{"X":26.0,"Y":32.0,"Z":0.0},"Mass":10816.0,"Velocity":{"X":0.0,"Y":0.0,"Z":0.0},"Force":{"X":0.0,"Y":0.0,"Z":0.0},"Density":9999.0,"IsGone":false,"BounceCount":0,"Radius":0.6368060297522375},{"Position":{"X":14.0,"Y":9.0,"Z":0.0},"Mass":10592.0,"Velocity":{"X":0.0,"Y":0.0,"Z":0.0},"Force":{"X":0.0,"Y":0.0,"Z":0.0},"Density":9999.0,"IsGone":false,"BounceCount":0,"Radius":0.6323792310265679},{"Position":{"X":-41.0,"Y":48.0,"Z":0.0},"Mass":16702.0,"Velocity":{"X":0.0,"Y":0.0,"Z":0.0},"Force":{"X":0.0,"Y":0.0,"Z":0.0},"Density":9999.0,"IsGone":false,"BounceCount":0,"Radius":0.736050762982585},{"Position":{"X":-50.0,"Y":-60.0,"Z":0.0},"Mass":10000000000.0,"Velocity":{"X":0.1,"Y":0.0,"Z":0.0},"Force":{"X":0.0,"Y":0.0,"Z":0.0},"Density":1000000000.0,"IsGone":false,"BounceCount":0,"Radius":1.3365046175719757}]